{
  "$schema": "https://developer.microsoft.com/json-schemas/fabric/item/report/definition/visualContainer/2.10.0/schema.json",
  "name": "88f199b41e350131378b",
  "position": {
    "x": 0,
    "y": 76.60898035856053,
    "z": 1000,
    "height": 65.1164639252814,
    "width": 252.32629771046541,
    "tabOrder": 0
  },
  "visual": {
    "visualType": "lineChart",
    "query": {
      "queryState": {
        "Category": {
          "projections": [
            {
              "field": {
                "HierarchyLevel": {
                  "Expression": {
                    "Hierarchy": {
                      "Expression": {
                        "PropertyVariationSource": {
                          "Expression": {
                            "SourceRef": {
                              "Entity": "dim_date"
                            }
                          },
                          "Name": "Variation",
                          "Property": "date"
                        }
                      },
                      "Hierarchy": "Date Hierarchy"
                    }
                  },
                  "Level": "Month"
                }
              },
              "queryRef": "dim_date.date.Variation.Date Hierarchy.Month",
              "nativeQueryRef": "date Month",
              "active": true
            }
          ]
        },
        "Y": {
          "projections": [
            {
              "field": {
                "Measure": {
                  "Expression": {
                    "SourceRef": {
                      "Entity": "_Measures"
                    }
                  },
                  "Property": "Total MRR"
                }
              },
              "queryRef": "_Measures.Total MRR",
              "nativeQueryRef": "Total MRR"
            }
          ]
        }
      }
    },
    "objects": {
      "valueAxis": [
        {
          "properties": {
            "showAxisTitle": {
              "expr": {
                "Literal": {
                  "Value": "false"
                }
              }
            },
            "show": {
              "expr": {
                "Literal": {
                  "Value": "false"
                }
              }
            }
          }
        }
      ],
      "lineStyles": [
        {
          "properties": {
            "lineStyle": {
              "expr": {
                "Literal": {
                  "Value": "'solid'"
                }
              }
            },
            "strokeLineJoin": {
              "expr": {
                "Literal": {
                  "Value": "'round'"
                }
              }
            },
            "strokeWidth": {
              "expr": {
                "Literal": {
                  "Value": "2D"
                }
              }
            },
            "lineChartType": {
              "expr": {
                "Literal": {
                  "Value": "'linear'"
                }
              }
            }
          }
        }
      ]
    },
    "visualContainerObjects": {
      "title": [
        {
          "properties": {
            "show": {
              "expr": {
                "Literal": {
                  "Value": "false"
                }
              }
            }
          }
        }
      ],
      "background": [
        {
          "properties": {
            "show": {
              "expr": {
                "Literal": {
                  "Value": "false"
                }
              }
            }
          }
        }
      ],
      "border": [
        {
          "properties": {
            "show": {
              "expr": {
                "Literal": {
                  "Value": "false"
                }
              }
            }
          }
        }
      ]
    },
    "drillFilterOtherVisuals": true
  },
  "parentGroupName": "8afbf59f6fa9c3977ee1"
}